pyjetbrains/__init__.py
pyjetbrains/pyjetbrains.py
pyjetbrains/pyjetbrains.pyi
pyjetbrains-1.1.0.dist-info/METADATA
pyjetbrains-1.1.0.dist-info/WHEEL
pyjetbrains-1.1.0.dist-info/licenses/LICENSE
pyjetbrains-1.1.0.dist-info/RECORD
