Metadata-Version: 2.1
Name: pyjetbrains
Version: 1.1.0
Summary: Python package to take control over JetBrains IDEs
Project-URL: Repository, https://github.com/KrazyManJ/pyjetbrains
Project-URL: Bug Tracker, https://github.com/KrazyManJ/pyjetbrains/issues
Author: KrazyManJ
License-File: LICENSE
Classifier: License :: OSI Approved :: MIT License
Classifier: Programming Language :: Python :: 3
Classifier: Typing :: Typed
Requires-Python: >=3.7
Requires-Dist: winapps
